{
  "gitSyncId": "68750378005e0954974296b0_ba0fa3d5-ab36-4908-9883-e697f47afbad",
  "id": "Home Gestao Copy_JS_Tendencias.getTendenciaVenda",
  "pluginId": "js-plugin",
  "pluginType": "JS",
  "unpublishedAction": {
    "actionConfiguration": {
      "encodeParamsToggle": true,
      "jsArguments": [],
      "paginationType": "NONE",
      "timeoutInMillisecond": 10000
    },
    "collectionId": "Home Gestao Copy_JS_Tendencias",
    "confirmBeforeExecute": false,
    "datasource": {
      "isAutoGenerated": false,
      "name": "UNUSED_DATASOURCE",
      "pluginId": "js-plugin"
    },
    "dynamicBindingPathList": [
      {
        "key": "body"
      }
    ],
    "executeOnLoad": false,
    "fullyQualifiedName": "JS_Tendencias.getTendenciaVenda",
    "name": "getTendenciaVenda",
    "pageId": "Home Gestao Copy",
    "userSetOnLoad": false
  }
}