{
  "animateLoading": true,
  "borderRadius": "0.375rem",
  "bottomRow": 14,
  "boxShadow": "none",
  "buttonVariant": "PRIMARY",
  "childStylesheet": {
    "button": {
      "buttonColor": "{{appsmith.theme.colors.primaryColor}}"
    }
  },
  "dynamicBindingPathList": [],
  "dynamicPropertyPathList": [
    {
      "key": "groupButtons.groupButton2.onClick"
    },
    {
      "key": "groupButtons.groupButton3.onClick"
    }
  ],
  "dynamicTriggerPathList": [
    {
      "key": "groupButtons.groupButton2.onClick"
    },
    {
      "key": "groupButtons.groupButton3.onClick"
    }
  ],
  "groupButtons": {
    "groupButton2": {
      "buttonColor": "#231f20",
      "buttonType": "SIMPLE",
      "disabledWhenInvalid": false,
      "iconName": "log-out",
      "id": "groupButton2",
      "index": 1,
      "isDisabled": false,
      "isVisible": true,
      "label": "Sair",
      "menuItems": {},
      "onClick": "{{Insert_Log_Logout.run(() => {\n  Object.keys(appsmith.store).forEach(k => removeValue(k));\n  navigateTo(\"Login\");\n}, (err) => {\n  showAlert(\"Erro ao registrar logout: \" + err.message, \"error\");\n});}}",
      "placement": "CENTER",
      "widgetId": ""
    },
    "groupButton3": {
      "buttonColor": "",
      "buttonType": "SIMPLE",
      "disabledWhenInvalid": false,
      "iconName": "cog",
      "id": "groupButton3",
      "index": 0,
      "isDisabled": false,
      "isVisible": true,
      "label": "",
      "menuItems": {
        "menuItem1": {
          "backgroundColor": "#FFFFFF",
          "disabledWhenInvalid": false,
          "id": "menuItem1",
          "index": 0,
          "isDisabled": false,
          "isVisible": true,
          "label": "First Option",
          "onClick": "",
          "widgetId": ""
        },
        "menuItem2": {
          "backgroundColor": "#FFFFFF",
          "disabledWhenInvalid": false,
          "id": "menuItem2",
          "index": 1,
          "isDisabled": false,
          "isVisible": true,
          "label": "Second Option",
          "onClick": "",
          "widgetId": ""
        },
        "menuItem3": {
          "backgroundColor": "#DD4B34",
          "disabledWhenInvalid": false,
          "iconAlign": "right",
          "iconColor": "#FFFFFF",
          "iconName": "trash",
          "id": "menuItem3",
          "index": 2,
          "isDisabled": false,
          "isVisible": true,
          "label": "Delete",
          "onClick": "",
          "textColor": "#FFFFFF",
          "widgetId": ""
        }
      },
      "onClick": "{{showModal(\"Modal_EditarSenha\")}}",
      "placement": "CENTER",
      "widgetId": ""
    }
  },
  "isCanvas": false,
  "isLoading": false,
  "isVisible": true,
  "key": "c3tesf85f9",
  "leftColumn": 44,
  "minWidth": 450,
  "mobileBottomRow": 15,
  "mobileLeftColumn": 28,
  "mobileRightColumn": 52,
  "mobileTopRow": 11,
  "needsErrorInfo": false,
  "orientation": "horizontal",
  "originalBottomRow": 14,
  "originalTopRow": 10,
  "parentColumnSpace": 6.84375,
  "parentId": "0",
  "parentRowSpace": 10,
  "renderMode": "CANVAS",
  "responsiveBehavior": "fill",
  "rightColumn": 63,
  "topRow": 10,
  "type": "BUTTON_GROUP_WIDGET",
  "version": 1,
  "widgetId": "7xyl0cdhvx",
  "widgetName": "ButtonGroup2"
}