{
  "gitSyncId": "68750378005e0954974296b0_d1d70402-e3dd-4057-b1ed-bc558ee3b2b2",
  "id": "Home Gestao Copy_JS_TendenciaGestao.getBateMetaTexto",
  "pluginId": "js-plugin",
  "pluginType": "JS",
  "unpublishedAction": {
    "actionConfiguration": {
      "encodeParamsToggle": true,
      "jsArguments": [],
      "paginationType": "NONE",
      "timeoutInMillisecond": 10000
    },
    "collectionId": "Home Gestao Copy_JS_TendenciaGestao",
    "confirmBeforeExecute": false,
    "datasource": {
      "isAutoGenerated": false,
      "name": "UNUSED_DATASOURCE",
      "pluginId": "js-plugin"
    },
    "dynamicBindingPathList": [
      {
        "key": "body"
      }
    ],
    "fullyQualifiedName": "JS_TendenciaGestao.getBateMetaTexto",
    "name": "getBateMetaTexto",
    "pageId": "Home Gestao Copy",
    "runBehaviour": "MANUAL",
    "userSetOnLoad": false
  }
}